{"nodes": [{"id": "v_code_projectcode_codeledger_src_handlers_platforms_leetcode_index_js", "label": "index.js", "file_type": "code", "source_file": "V:\\Code\\ProjectCode\\CodeLedger\\src\\handlers\\platforms\\leetcode\\index.js", "source_location": "L1"}, {"id": "index_langext", "label": "langExt()", "file_type": "code", "source_file": "V:\\Code\\ProjectCode\\CodeLedger\\src\\handlers\\platforms\\leetcode\\index.js", "source_location": "L43"}, {"id": "index_resolvelang", "label": "resolveLang()", "file_type": "code", "source_file": "V:\\Code\\ProjectCode\\CodeLedger\\src\\handlers\\platforms\\leetcode\\index.js", "source_location": "L48"}, {"id": "index_leetcodehandler", "label": "LeetCodeHandler", "file_type": "code", "source_file": "V:\\Code\\ProjectCode\\CodeLedger\\src\\handlers\\platforms\\leetcode\\index.js", "source_location": "L60"}, {"id": "index_leetcodehandler_constructor", "label": ".constructor()", "file_type": "code", "source_file": "V:\\Code\\ProjectCode\\CodeLedger\\src\\handlers\\platforms\\leetcode\\index.js", "source_location": "L61"}, {"id": "index_leetcodehandler_getdefaultprompt", "label": ".getDefaultPrompt()", "file_type": "code", "source_file": "V:\\Code\\ProjectCode\\CodeLedger\\src\\handlers\\platforms\\leetcode\\index.js", "source_location": "L69"}, {"id": "index_leetcodehandler_getsettingsschema", "label": ".getSettingsSchema()", "file_type": "code", "source_file": "V:\\Code\\ProjectCode\\CodeLedger\\src\\handlers\\platforms\\leetcode\\index.js", "source_location": "L81"}, {"id": "index_leetcodehandler_init", "label": ".init()", "file_type": "code", "source_file": "V:\\Code\\ProjectCode\\CodeLedger\\src\\handlers\\platforms\\leetcode\\index.js", "source_location": "L110"}, {"id": "index_leetcodehandler_setupmutationobserver", "label": "._setupMutationObserver()", "file_type": "code", "source_file": "V:\\Code\\ProjectCode\\CodeLedger\\src\\handlers\\platforms\\leetcode\\index.js", "source_location": "L128"}, {"id": "index_leetcodehandler_injectmanualsyncbtn", "label": "._injectManualSyncBtn()", "file_type": "code", "source_file": "V:\\Code\\ProjectCode\\CodeLedger\\src\\handlers\\platforms\\leetcode\\index.js", "source_location": "L138"}, {"id": "index_leetcodehandler_manualsync", "label": "._manualSync()", "file_type": "code", "source_file": "V:\\Code\\ProjectCode\\CodeLedger\\src\\handlers\\platforms\\leetcode\\index.js", "source_location": "L163"}, {"id": "index_leetcodehandler_checksubmission", "label": "._checkSubmission()", "file_type": "code", "source_file": "V:\\Code\\ProjectCode\\CodeLedger\\src\\handlers\\platforms\\leetcode\\index.js", "source_location": "L176"}, {"id": "index_leetcodehandler_isacceptedvisible", "label": "._isAcceptedVisible()", "file_type": "code", "source_file": "V:\\Code\\ProjectCode\\CodeLedger\\src\\handlers\\platforms\\leetcode\\index.js", "source_location": "L196"}, {"id": "index_leetcodehandler_processsubmission", "label": "._processSubmission()", "file_type": "code", "source_file": "V:\\Code\\ProjectCode\\CodeLedger\\src\\handlers\\platforms\\leetcode\\index.js", "source_location": "L226"}, {"id": "index_leetcodehandler_buildfileset", "label": "._buildFileSet()", "file_type": "code", "source_file": "V:\\Code\\ProjectCode\\CodeLedger\\src\\handlers\\platforms\\leetcode\\index.js", "source_location": "L312"}, {"id": "index_leetcodehandler_formatstats", "label": "._formatStats()", "file_type": "code", "source_file": "V:\\Code\\ProjectCode\\CodeLedger\\src\\handlers\\platforms\\leetcode\\index.js", "source_location": "L372"}, {"id": "index_leetcodehandler_formatsimilar", "label": "._formatSimilar()", "file_type": "code", "source_file": "V:\\Code\\ProjectCode\\CodeLedger\\src\\handlers\\platforms\\leetcode\\index.js", "source_location": "L380"}, {"id": "index_leetcodehandler_formathints", "label": "._formatHints()", "file_type": "code", "source_file": "V:\\Code\\ProjectCode\\CodeLedger\\src\\handlers\\platforms\\leetcode\\index.js", "source_location": "L392"}, {"id": "index_leetcodehandler_fetchmetadata", "label": "._fetchMetadata()", "file_type": "code", "source_file": "V:\\Code\\ProjectCode\\CodeLedger\\src\\handlers\\platforms\\leetcode\\index.js", "source_location": "L398"}, {"id": "index_leetcodehandler_gql", "label": "._gql()", "file_type": "code", "source_file": "V:\\Code\\ProjectCode\\CodeLedger\\src\\handlers\\platforms\\leetcode\\index.js", "source_location": "L407"}, {"id": "index_leetcodehandler_fetchgraphql", "label": ".fetchGraphQL()", "file_type": "code", "source_file": "V:\\Code\\ProjectCode\\CodeLedger\\src\\handlers\\platforms\\leetcode\\index.js", "source_location": "L424"}, {"id": "index_leetcodehandler_getproblemmetadata", "label": ".getProblemMetadata()", "file_type": "code", "source_file": "V:\\Code\\ProjectCode\\CodeLedger\\src\\handlers\\platforms\\leetcode\\index.js", "source_location": "L425"}], "edges": [{"source": "v_code_projectcode_codeledger_src_handlers_platforms_leetcode_index_js", "target": "v_code_projectcode_codeledger_src_handlers_base_baseplatformhandler_ts", "relation": "imports_from", "confidence": "EXTRACTED", "source_file": "V:\\Code\\ProjectCode\\CodeLedger\\src\\handlers\\platforms\\leetcode\\index.js", "source_location": "L6", "weight": 1.0}, {"source": "v_code_projectcode_codeledger_src_handlers_platforms_leetcode_index_js", "target": "v_code_projectcode_codeledger_src_handlers_platforms_leetcode_dom_selectors_ts", "relation": "imports_from", "confidence": "EXTRACTED", "source_file": "V:\\Code\\ProjectCode\\CodeLedger\\src\\handlers\\platforms\\leetcode\\index.js", "source_location": "L7", "weight": 1.0}, {"source": "v_code_projectcode_codeledger_src_handlers_platforms_leetcode_index_js", "target": "v_code_projectcode_codeledger_src_handlers_platforms_leetcode_page_detector_ts", "relation": "imports_from", "confidence": "EXTRACTED", "source_file": "V:\\Code\\ProjectCode\\CodeLedger\\src\\handlers\\platforms\\leetcode\\index.js", "source_location": "L8", "weight": 1.0}, {"source": "v_code_projectcode_codeledger_src_handlers_platforms_leetcode_index_js", "target": "v_code_projectcode_codeledger_src_handlers_platforms_leetcode_graphql_queries_ts", "relation": "imports_from", "confidence": "EXTRACTED", "source_file": "V:\\Code\\ProjectCode\\CodeLedger\\src\\handlers\\platforms\\leetcode\\index.js", "source_location": "L9", "weight": 1.0}, {"source": "v_code_projectcode_codeledger_src_handlers_platforms_leetcode_index_js", "target": "v_code_projectcode_codeledger_src_core_event_bus_ts", "relation": "imports_from", "confidence": "EXTRACTED", "source_file": "V:\\Code\\ProjectCode\\CodeLedger\\src\\handlers\\platforms\\leetcode\\index.js", "source_location": "L10", "weight": 1.0}, {"source": "v_code_projectcode_codeledger_src_handlers_platforms_leetcode_index_js", "target": "v_code_projectcode_codeledger_src_handlers_platforms_leetcode_qol_ts", "relation": "imports_from", "confidence": "EXTRACTED", "source_file": "V:\\Code\\ProjectCode\\CodeLedger\\src\\handlers\\platforms\\leetcode\\index.js", "source_location": "L11", "weight": 1.0}, {"source": "v_code_projectcode_codeledger_src_handlers_platforms_leetcode_index_js", "target": "v_code_projectcode_codeledger_src_core_storage_ts", "relation": "imports_from", "confidence": "EXTRACTED", "source_file": "V:\\Code\\ProjectCode\\CodeLedger\\src\\handlers\\platforms\\leetcode\\index.js", "source_location": "L12", "weight": 1.0}, {"source": "v_code_projectcode_codeledger_src_handlers_platforms_leetcode_index_js", "target": "v_code_projectcode_codeledger_src_core_canonical_mapper_ts", "relation": "imports_from", "confidence": "EXTRACTED", "source_file": "V:\\Code\\ProjectCode\\CodeLedger\\src\\handlers\\platforms\\leetcode\\index.js", "source_location": "L13", "weight": 1.0}, {"source": "v_code_projectcode_codeledger_src_handlers_platforms_leetcode_index_js", "target": "v_code_projectcode_codeledger_src_lib_debug_ts", "relation": "imports_from", "confidence": "EXTRACTED", "source_file": "V:\\Code\\ProjectCode\\CodeLedger\\src\\handlers\\platforms\\leetcode\\index.js", "source_location": "L14", "weight": 1.0}, {"source": "v_code_projectcode_codeledger_src_handlers_platforms_leetcode_index_js", "target": "v_code_projectcode_codeledger_src_core_ai_prompts_ts", "relation": "imports_from", "confidence": "EXTRACTED", "source_file": "V:\\Code\\ProjectCode\\CodeLedger\\src\\handlers\\platforms\\leetcode\\index.js", "source_location": "L15", "weight": 1.0}, {"source": "v_code_projectcode_codeledger_src_handlers_platforms_leetcode_index_js", "target": "index_langext", "relation": "contains", "confidence": "EXTRACTED", "source_file": "V:\\Code\\ProjectCode\\CodeLedger\\src\\handlers\\platforms\\leetcode\\index.js", "source_location": "L43", "weight": 1.0}, {"source": "v_code_projectcode_codeledger_src_handlers_platforms_leetcode_index_js", "target": "index_resolvelang", "relation": "contains", "confidence": "EXTRACTED", "source_file": "V:\\Code\\ProjectCode\\CodeLedger\\src\\handlers\\platforms\\leetcode\\index.js", "source_location": "L48", "weight": 1.0}, {"source": "v_code_projectcode_codeledger_src_handlers_platforms_leetcode_index_js", "target": "index_leetcodehandler", "relation": "contains", "confidence": "EXTRACTED", "source_file": "V:\\Code\\ProjectCode\\CodeLedger\\src\\handlers\\platforms\\leetcode\\index.js", "source_location": "L60", "weight": 1.0}, {"source": "index_leetcodehandler", "target": "index_leetcodehandler_constructor", "relation": "method", "confidence": "EXTRACTED", "source_file": "V:\\Code\\ProjectCode\\CodeLedger\\src\\handlers\\platforms\\leetcode\\index.js", "source_location": "L61", "weight": 1.0}, {"source": "index_leetcodehandler", "target": "index_leetcodehandler_getdefaultprompt", "relation": "method", "confidence": "EXTRACTED", "source_file": "V:\\Code\\ProjectCode\\CodeLedger\\src\\handlers\\platforms\\leetcode\\index.js", "source_location": "L69", "weight": 1.0}, {"source": "index_leetcodehandler", "target": "index_leetcodehandler_getsettingsschema", "relation": "method", "confidence": "EXTRACTED", "source_file": "V:\\Code\\ProjectCode\\CodeLedger\\src\\handlers\\platforms\\leetcode\\index.js", "source_location": "L81", "weight": 1.0}, {"source": "index_leetcodehandler", "target": "index_leetcodehandler_init", "relation": "method", "confidence": "EXTRACTED", "source_file": "V:\\Code\\ProjectCode\\CodeLedger\\src\\handlers\\platforms\\leetcode\\index.js", "source_location": "L110", "weight": 1.0}, {"source": "index_leetcodehandler", "target": "index_leetcodehandler_setupmutationobserver", "relation": "method", "confidence": "EXTRACTED", "source_file": "V:\\Code\\ProjectCode\\CodeLedger\\src\\handlers\\platforms\\leetcode\\index.js", "source_location": "L128", "weight": 1.0}, {"source": "index_leetcodehandler", "target": "index_leetcodehandler_injectmanualsyncbtn", "relation": "method", "confidence": "EXTRACTED", "source_file": "V:\\Code\\ProjectCode\\CodeLedger\\src\\handlers\\platforms\\leetcode\\index.js", "source_location": "L138", "weight": 1.0}, {"source": "index_leetcodehandler", "target": "index_leetcodehandler_manualsync", "relation": "method", "confidence": "EXTRACTED", "source_file": "V:\\Code\\ProjectCode\\CodeLedger\\src\\handlers\\platforms\\leetcode\\index.js", "source_location": "L163", "weight": 1.0}, {"source": "index_leetcodehandler", "target": "index_leetcodehandler_checksubmission", "relation": "method", "confidence": "EXTRACTED", "source_file": "V:\\Code\\ProjectCode\\CodeLedger\\src\\handlers\\platforms\\leetcode\\index.js", "source_location": "L176", "weight": 1.0}, {"source": "index_leetcodehandler", "target": "index_leetcodehandler_isacceptedvisible", "relation": "method", "confidence": "EXTRACTED", "source_file": "V:\\Code\\ProjectCode\\CodeLedger\\src\\handlers\\platforms\\leetcode\\index.js", "source_location": "L196", "weight": 1.0}, {"source": "index_leetcodehandler", "target": "index_leetcodehandler_processsubmission", "relation": "method", "confidence": "EXTRACTED", "source_file": "V:\\Code\\ProjectCode\\CodeLedger\\src\\handlers\\platforms\\leetcode\\index.js", "source_location": "L226", "weight": 1.0}, {"source": "index_leetcodehandler", "target": "index_leetcodehandler_buildfileset", "relation": "method", "confidence": "EXTRACTED", "source_file": "V:\\Code\\ProjectCode\\CodeLedger\\src\\handlers\\platforms\\leetcode\\index.js", "source_location": "L312", "weight": 1.0}, {"source": "index_leetcodehandler", "target": "index_leetcodehandler_formatstats", "relation": "method", "confidence": "EXTRACTED", "source_file": "V:\\Code\\ProjectCode\\CodeLedger\\src\\handlers\\platforms\\leetcode\\index.js", "source_location": "L372", "weight": 1.0}, {"source": "index_leetcodehandler", "target": "index_leetcodehandler_formatsimilar", "relation": "method", "confidence": "EXTRACTED", "source_file": "V:\\Code\\ProjectCode\\CodeLedger\\src\\handlers\\platforms\\leetcode\\index.js", "source_location": "L380", "weight": 1.0}, {"source": "index_leetcodehandler", "target": "index_leetcodehandler_formathints", "relation": "method", "confidence": "EXTRACTED", "source_file": "V:\\Code\\ProjectCode\\CodeLedger\\src\\handlers\\platforms\\leetcode\\index.js", "source_location": "L392", "weight": 1.0}, {"source": "index_leetcodehandler", "target": "index_leetcodehandler_fetchmetadata", "relation": "method", "confidence": "EXTRACTED", "source_file": "V:\\Code\\ProjectCode\\CodeLedger\\src\\handlers\\platforms\\leetcode\\index.js", "source_location": "L398", "weight": 1.0}, {"source": "index_leetcodehandler", "target": "index_leetcodehandler_gql", "relation": "method", "confidence": "EXTRACTED", "source_file": "V:\\Code\\ProjectCode\\CodeLedger\\src\\handlers\\platforms\\leetcode\\index.js", "source_location": "L407", "weight": 1.0}, {"source": "index_leetcodehandler", "target": "index_leetcodehandler_checksubmission", "relation": "method", "confidence": "EXTRACTED", "source_file": "V:\\Code\\ProjectCode\\CodeLedger\\src\\handlers\\platforms\\leetcode\\index.js", "source_location": "L423", "weight": 1.0}, {"source": "index_leetcodehandler", "target": "index_leetcodehandler_fetchgraphql", "relation": "method", "confidence": "EXTRACTED", "source_file": "V:\\Code\\ProjectCode\\CodeLedger\\src\\handlers\\platforms\\leetcode\\index.js", "source_location": "L424", "weight": 1.0}, {"source": "index_leetcodehandler", "target": "index_leetcodehandler_getproblemmetadata", "relation": "method", "confidence": "EXTRACTED", "source_file": "V:\\Code\\ProjectCode\\CodeLedger\\src\\handlers\\platforms\\leetcode\\index.js", "source_location": "L425", "weight": 1.0}, {"source": "index_resolvelang", "target": "index_langext", "relation": "calls", "confidence": "EXTRACTED", "source_file": "V:\\Code\\ProjectCode\\CodeLedger\\src\\handlers\\platforms\\leetcode\\index.js", "source_location": "L52", "weight": 1.0}, {"source": "index_leetcodehandler_constructor", "target": "index_leetcodehandler_getdefaultprompt", "relation": "calls", "confidence": "EXTRACTED", "source_file": "V:\\Code\\ProjectCode\\CodeLedger\\src\\handlers\\platforms\\leetcode\\index.js", "source_location": "L66", "weight": 1.0}, {"source": "index_leetcodehandler_init", "target": "index_leetcodehandler_setupmutationobserver", "relation": "calls", "confidence": "EXTRACTED", "source_file": "V:\\Code\\ProjectCode\\CodeLedger\\src\\handlers\\platforms\\leetcode\\index.js", "source_location": "L112", "weight": 1.0}, {"source": "index_leetcodehandler_init", "target": "index_leetcodehandler_injectmanualsyncbtn", "relation": "calls", "confidence": "EXTRACTED", "source_file": "V:\\Code\\ProjectCode\\CodeLedger\\src\\handlers\\platforms\\leetcode\\index.js", "source_location": "L113", "weight": 1.0}, {"source": "index_leetcodehandler_manualsync", "target": "index_leetcodehandler_processsubmission", "relation": "calls", "confidence": "EXTRACTED", "source_file": "V:\\Code\\ProjectCode\\CodeLedger\\src\\handlers\\platforms\\leetcode\\index.js", "source_location": "L167", "weight": 1.0}, {"source": "index_leetcodehandler_checksubmission", "target": "index_leetcodehandler_isacceptedvisible", "relation": "calls", "confidence": "EXTRACTED", "source_file": "V:\\Code\\ProjectCode\\CodeLedger\\src\\handlers\\platforms\\leetcode\\index.js", "source_location": "L184", "weight": 1.0}, {"source": "index_leetcodehandler_checksubmission", "target": "index_leetcodehandler_processsubmission", "relation": "calls", "confidence": "EXTRACTED", "source_file": "V:\\Code\\ProjectCode\\CodeLedger\\src\\handlers\\platforms\\leetcode\\index.js", "source_location": "L187", "weight": 1.0}, {"source": "index_leetcodehandler_processsubmission", "target": "index_leetcodehandler_gql", "relation": "calls", "confidence": "EXTRACTED", "source_file": "V:\\Code\\ProjectCode\\CodeLedger\\src\\handlers\\platforms\\leetcode\\index.js", "source_location": "L236", "weight": 1.0}, {"source": "index_leetcodehandler_processsubmission", "target": "index_leetcodehandler_fetchmetadata", "relation": "calls", "confidence": "EXTRACTED", "source_file": "V:\\Code\\ProjectCode\\CodeLedger\\src\\handlers\\platforms\\leetcode\\index.js", "source_location": "L269", "weight": 1.0}, {"source": "index_leetcodehandler_processsubmission", "target": "index_leetcodehandler_buildfileset", "relation": "calls", "confidence": "EXTRACTED", "source_file": "V:\\Code\\ProjectCode\\CodeLedger\\src\\handlers\\platforms\\leetcode\\index.js", "source_location": "L272", "weight": 1.0}, {"source": "index_leetcodehandler_processsubmission", "target": "index_resolvelang", "relation": "calls", "confidence": "EXTRACTED", "source_file": "V:\\Code\\ProjectCode\\CodeLedger\\src\\handlers\\platforms\\leetcode\\index.js", "source_location": "L278", "weight": 1.0}, {"source": "index_leetcodehandler_buildfileset", "target": "index_resolvelang", "relation": "calls", "confidence": "EXTRACTED", "source_file": "V:\\Code\\ProjectCode\\CodeLedger\\src\\handlers\\platforms\\leetcode\\index.js", "source_location": "L313", "weight": 1.0}, {"source": "index_leetcodehandler_buildfileset", "target": "index_leetcodehandler_formatstats", "relation": "calls", "confidence": "EXTRACTED", "source_file": "V:\\Code\\ProjectCode\\CodeLedger\\src\\handlers\\platforms\\leetcode\\index.js", "source_location": "L328", "weight": 1.0}, {"source": "index_leetcodehandler_buildfileset", "target": "index_leetcodehandler_formatsimilar", "relation": "calls", "confidence": "EXTRACTED", "source_file": "V:\\Code\\ProjectCode\\CodeLedger\\src\\handlers\\platforms\\leetcode\\index.js", "source_location": "L329", "weight": 1.0}, {"source": "index_leetcodehandler_buildfileset", "target": "index_leetcodehandler_formathints", "relation": "calls", "confidence": "EXTRACTED", "source_file": "V:\\Code\\ProjectCode\\CodeLedger\\src\\handlers\\platforms\\leetcode\\index.js", "source_location": "L330", "weight": 1.0}, {"source": "index_leetcodehandler_fetchmetadata", "target": "index_leetcodehandler_gql", "relation": "calls", "confidence": "EXTRACTED", "source_file": "V:\\Code\\ProjectCode\\CodeLedger\\src\\handlers\\platforms\\leetcode\\index.js", "source_location": "L400", "weight": 1.0}, {"source": "index_leetcodehandler_fetchgraphql", "target": "index_leetcodehandler_gql", "relation": "calls", "confidence": "EXTRACTED", "source_file": "V:\\Code\\ProjectCode\\CodeLedger\\src\\handlers\\platforms\\leetcode\\index.js", "source_location": "L424", "weight": 1.0}, {"source": "index_leetcodehandler_getproblemmetadata", "target": "index_leetcodehandler_fetchmetadata", "relation": "calls", "confidence": "EXTRACTED", "source_file": "V:\\Code\\ProjectCode\\CodeLedger\\src\\handlers\\platforms\\leetcode\\index.js", "source_location": "L425", "weight": 1.0}], "raw_calls": [{"caller_nid": "index_langext", "callee": "replace", "source_file": "V:\\Code\\ProjectCode\\CodeLedger\\src\\handlers\\platforms\\leetcode\\index.js", "source_location": "L44"}, {"caller_nid": "index_langext", "callee": "toLowerCase", "source_file": "V:\\Code\\ProjectCode\\CodeLedger\\src\\handlers\\platforms\\leetcode\\index.js", "source_location": "L44"}, {"caller_nid": "index_resolvelang", "callee": "replace", "source_file": "V:\\Code\\ProjectCode\\CodeLedger\\src\\handlers\\platforms\\leetcode\\index.js", "source_location": "L51"}, {"caller_nid": "index_resolvelang", "callee": "toLowerCase", "source_file": "V:\\Code\\ProjectCode\\CodeLedger\\src\\handlers\\platforms\\leetcode\\index.js", "source_location": "L51"}, {"caller_nid": "index_resolvelang", "callee": "replace", "source_file": "V:\\Code\\ProjectCode\\CodeLedger\\src\\handlers\\platforms\\leetcode\\index.js", "source_location": "L55"}, {"caller_nid": "index_resolvelang", "callee": "toLowerCase", "source_file": "V:\\Code\\ProjectCode\\CodeLedger\\src\\handlers\\platforms\\leetcode\\index.js", "source_location": "L55"}, {"caller_nid": "index_leetcodehandler_constructor", "callee": "super", "source_file": "V:\\Code\\ProjectCode\\CodeLedger\\src\\handlers\\platforms\\leetcode\\index.js", "source_location": "L62"}, {"caller_nid": "index_leetcodehandler_constructor", "callee": "registerPlatformPrompt", "source_file": "V:\\Code\\ProjectCode\\CodeLedger\\src\\handlers\\platforms\\leetcode\\index.js", "source_location": "L66"}, {"caller_nid": "index_leetcodehandler_init", "callee": "log", "source_file": "V:\\Code\\ProjectCode\\CodeLedger\\src\\handlers\\platforms\\leetcode\\index.js", "source_location": "L111"}, {"caller_nid": "index_leetcodehandler_init", "callee": "detectPage", "source_file": "V:\\Code\\ProjectCode\\CodeLedger\\src\\handlers\\platforms\\leetcode\\index.js", "source_location": "L116"}, {"caller_nid": "index_leetcodehandler_init", "callee": "catch", "source_file": "V:\\Code\\ProjectCode\\CodeLedger\\src\\handlers\\platforms\\leetcode\\index.js", "source_location": "L118"}, {"caller_nid": "index_leetcodehandler_init", "callee": "then", "source_file": "V:\\Code\\ProjectCode\\CodeLedger\\src\\handlers\\platforms\\leetcode\\index.js", "source_location": "L118"}, {"caller_nid": "index_leetcodehandler_init", "callee": "getSettings", "source_file": "V:\\Code\\ProjectCode\\CodeLedger\\src\\handlers\\platforms\\leetcode\\index.js", "source_location": "L118"}, {"caller_nid": "index_leetcodehandler_setupmutationobserver", "callee": "observe", "source_file": "V:\\Code\\ProjectCode\\CodeLedger\\src\\handlers\\platforms\\leetcode\\index.js", "source_location": "L134"}, {"caller_nid": "index_leetcodehandler_injectmanualsyncbtn", "callee": "observe", "source_file": "V:\\Code\\ProjectCode\\CodeLedger\\src\\handlers\\platforms\\leetcode\\index.js", "source_location": "L160"}, {"caller_nid": "index_leetcodehandler_manualsync", "callee": "getElementById", "source_file": "V:\\Code\\ProjectCode\\CodeLedger\\src\\handlers\\platforms\\leetcode\\index.js", "source_location": "L164"}, {"caller_nid": "index_leetcodehandler_manualsync", "callee": "setTimeout", "source_file": "V:\\Code\\ProjectCode\\CodeLedger\\src\\handlers\\platforms\\leetcode\\index.js", "source_location": "L168"}, {"caller_nid": "index_leetcodehandler_manualsync", "callee": "error", "source_file": "V:\\Code\\ProjectCode\\CodeLedger\\src\\handlers\\platforms\\leetcode\\index.js", "source_location": "L170"}, {"caller_nid": "index_leetcodehandler_checksubmission", "callee": "detectPage", "source_file": "V:\\Code\\ProjectCode\\CodeLedger\\src\\handlers\\platforms\\leetcode\\index.js", "source_location": "L179"}, {"caller_nid": "index_leetcodehandler_isacceptedvisible", "callee": "safeQuery", "source_file": "V:\\Code\\ProjectCode\\CodeLedger\\src\\handlers\\platforms\\leetcode\\index.js", "source_location": "L198"}, {"caller_nid": "index_leetcodehandler_isacceptedvisible", "callee": "test", "source_file": "V:\\Code\\ProjectCode\\CodeLedger\\src\\handlers\\platforms\\leetcode\\index.js", "source_location": "L199"}, {"caller_nid": "index_leetcodehandler_isacceptedvisible", "callee": "filter", "source_file": "V:\\Code\\ProjectCode\\CodeLedger\\src\\handlers\\platforms\\leetcode\\index.js", "source_location": "L203"}, {"caller_nid": "index_leetcodehandler_isacceptedvisible", "callee": "querySelector", "source_file": "V:\\Code\\ProjectCode\\CodeLedger\\src\\handlers\\platforms\\leetcode\\index.js", "source_location": "L204"}, {"caller_nid": "index_leetcodehandler_isacceptedvisible", "callee": "querySelector", "source_file": "V:\\Code\\ProjectCode\\CodeLedger\\src\\handlers\\platforms\\leetcode\\index.js", "source_location": "L205"}, {"caller_nid": "index_leetcodehandler_isacceptedvisible", "callee": "querySelector", "source_file": "V:\\Code\\ProjectCode\\CodeLedger\\src\\handlers\\platforms\\leetcode\\index.js", "source_location": "L206"}, {"caller_nid": "index_leetcodehandler_isacceptedvisible", "callee": "querySelector", "source_file": "V:\\Code\\ProjectCode\\CodeLedger\\src\\handlers\\platforms\\leetcode\\index.js", "source_location": "L207"}, {"caller_nid": "index_leetcodehandler_isacceptedvisible", "callee": "createTreeWalker", "source_file": "V:\\Code\\ProjectCode\\CodeLedger\\src\\handlers\\platforms\\leetcode\\index.js", "source_location": "L212"}, {"caller_nid": "index_leetcodehandler_isacceptedvisible", "callee": "nextNode", "source_file": "V:\\Code\\ProjectCode\\CodeLedger\\src\\handlers\\platforms\\leetcode\\index.js", "source_location": "L214"}, {"caller_nid": "index_leetcodehandler_isacceptedvisible", "callee": "test", "source_file": "V:\\Code\\ProjectCode\\CodeLedger\\src\\handlers\\platforms\\leetcode\\index.js", "source_location": "L215"}, {"caller_nid": "index_leetcodehandler_processsubmission", "callee": "getSettings", "source_file": "V:\\Code\\ProjectCode\\CodeLedger\\src\\handlers\\platforms\\leetcode\\index.js", "source_location": "L229"}, {"caller_nid": "index_leetcodehandler_processsubmission", "callee": "find", "source_file": "V:\\Code\\ProjectCode\\CodeLedger\\src\\handlers\\platforms\\leetcode\\index.js", "source_location": "L245"}, {"caller_nid": "index_leetcodehandler_processsubmission", "callee": "getItem", "source_file": "V:\\Code\\ProjectCode\\CodeLedger\\src\\handlers\\platforms\\leetcode\\index.js", "source_location": "L250"}, {"caller_nid": "index_leetcodehandler_processsubmission", "callee": "String", "source_file": "V:\\Code\\ProjectCode\\CodeLedger\\src\\handlers\\platforms\\leetcode\\index.js", "source_location": "L251"}, {"caller_nid": "index_leetcodehandler_processsubmission", "callee": "log", "source_file": "V:\\Code\\ProjectCode\\CodeLedger\\src\\handlers\\platforms\\leetcode\\index.js", "source_location": "L252"}, {"caller_nid": "index_leetcodehandler_processsubmission", "callee": "setItem", "source_file": "V:\\Code\\ProjectCode\\CodeLedger\\src\\handlers\\platforms\\leetcode\\index.js", "source_location": "L260"}, {"caller_nid": "index_leetcodehandler_processsubmission", "callee": "String", "source_file": "V:\\Code\\ProjectCode\\CodeLedger\\src\\handlers\\platforms\\leetcode\\index.js", "source_location": "L260"}, {"caller_nid": "index_leetcodehandler_processsubmission", "callee": "now", "source_file": "V:\\Code\\ProjectCode\\CodeLedger\\src\\handlers\\platforms\\leetcode\\index.js", "source_location": "L264"}, {"caller_nid": "index_leetcodehandler_processsubmission", "callee": "loadMap", "source_file": "V:\\Code\\ProjectCode\\CodeLedger\\src\\handlers\\platforms\\leetcode\\index.js", "source_location": "L275"}, {"caller_nid": "index_leetcodehandler_processsubmission", "callee": "resolve", "source_file": "V:\\Code\\ProjectCode\\CodeLedger\\src\\handlers\\platforms\\leetcode\\index.js", "source_location": "L276"}, {"caller_nid": "index_leetcodehandler_processsubmission", "callee": "emit", "source_file": "V:\\Code\\ProjectCode\\CodeLedger\\src\\handlers\\platforms\\leetcode\\index.js", "source_location": "L280"}, {"caller_nid": "index_leetcodehandler_processsubmission", "callee": "map", "source_file": "V:\\Code\\ProjectCode\\CodeLedger\\src\\handlers\\platforms\\leetcode\\index.js", "source_location": "L287"}, {"caller_nid": "index_leetcodehandler_processsubmission", "callee": "floor", "source_file": "V:\\Code\\ProjectCode\\CodeLedger\\src\\handlers\\platforms\\leetcode\\index.js", "source_location": "L296"}, {"caller_nid": "index_leetcodehandler_processsubmission", "callee": "now", "source_file": "V:\\Code\\ProjectCode\\CodeLedger\\src\\handlers\\platforms\\leetcode\\index.js", "source_location": "L296"}, {"caller_nid": "index_leetcodehandler_processsubmission", "callee": "filter", "source_file": "V:\\Code\\ProjectCode\\CodeLedger\\src\\handlers\\platforms\\leetcode\\index.js", "source_location": "L300"}, {"caller_nid": "index_leetcodehandler_processsubmission", "callee": "log", "source_file": "V:\\Code\\ProjectCode\\CodeLedger\\src\\handlers\\platforms\\leetcode\\index.js", "source_location": "L303"}, {"caller_nid": "index_leetcodehandler_processsubmission", "callee": "error", "source_file": "V:\\Code\\ProjectCode\\CodeLedger\\src\\handlers\\platforms\\leetcode\\index.js", "source_location": "L305"}, {"caller_nid": "index_leetcodehandler_buildfileset", "callee": "push", "source_file": "V:\\Code\\ProjectCode\\CodeLedger\\src\\handlers\\platforms\\leetcode\\index.js", "source_location": "L321"}, {"caller_nid": "index_leetcodehandler_buildfileset", "callee": "replace", "source_file": "V:\\Code\\ProjectCode\\CodeLedger\\src\\handlers\\platforms\\leetcode\\index.js", "source_location": "L322"}, {"caller_nid": "index_leetcodehandler_buildfileset", "callee": "push", "source_file": "V:\\Code\\ProjectCode\\CodeLedger\\src\\handlers\\platforms\\leetcode\\index.js", "source_location": "L332"}, {"caller_nid": "index_leetcodehandler_buildfileset", "callee": "join", "source_file": "V:\\Code\\ProjectCode\\CodeLedger\\src\\handlers\\platforms\\leetcode\\index.js", "source_location": "L334"}, {"caller_nid": "index_leetcodehandler_buildfileset", "callee": "filter", "source_file": "V:\\Code\\ProjectCode\\CodeLedger\\src\\handlers\\platforms\\leetcode\\index.js", "source_location": "L334"}, {"caller_nid": "index_leetcodehandler_buildfileset", "callee": "toFixed", "source_file": "V:\\Code\\ProjectCode\\CodeLedger\\src\\handlers\\platforms\\leetcode\\index.js", "source_location": "L337"}, {"caller_nid": "index_leetcodehandler_buildfileset", "callee": "join", "source_file": "V:\\Code\\ProjectCode\\CodeLedger\\src\\handlers\\platforms\\leetcode\\index.js", "source_location": "L339"}, {"caller_nid": "index_leetcodehandler_buildfileset", "callee": "map", "source_file": "V:\\Code\\ProjectCode\\CodeLedger\\src\\handlers\\platforms\\leetcode\\index.js", "source_location": "L339"}, {"caller_nid": "index_leetcodehandler_buildfileset", "callee": "trim", "source_file": "V:\\Code\\ProjectCode\\CodeLedger\\src\\handlers\\platforms\\leetcode\\index.js", "source_location": "L343"}, {"caller_nid": "index_leetcodehandler_buildfileset", "callee": "replace", "source_file": "V:\\Code\\ProjectCode\\CodeLedger\\src\\handlers\\platforms\\leetcode\\index.js", "source_location": "L343"}, {"caller_nid": "index_leetcodehandler_buildfileset", "callee": "replace", "source_file": "V:\\Code\\ProjectCode\\CodeLedger\\src\\handlers\\platforms\\leetcode\\index.js", "source_location": "L343"}, {"caller_nid": "index_leetcodehandler_buildfileset", "callee": "replace", "source_file": "V:\\Code\\ProjectCode\\CodeLedger\\src\\handlers\\platforms\\leetcode\\index.js", "source_location": "L343"}, {"caller_nid": "index_leetcodehandler_buildfileset", "callee": "replace", "source_file": "V:\\Code\\ProjectCode\\CodeLedger\\src\\handlers\\platforms\\leetcode\\index.js", "source_location": "L343"}, {"caller_nid": "index_leetcodehandler_buildfileset", "callee": "replace", "source_file": "V:\\Code\\ProjectCode\\CodeLedger\\src\\handlers\\platforms\\leetcode\\index.js", "source_location": "L343"}, {"caller_nid": "index_leetcodehandler_buildfileset", "callee": "replace", "source_file": "V:\\Code\\ProjectCode\\CodeLedger\\src\\handlers\\platforms\\leetcode\\index.js", "source_location": "L343"}, {"caller_nid": "index_leetcodehandler_buildfileset", "callee": "replace", "source_file": "V:\\Code\\ProjectCode\\CodeLedger\\src\\handlers\\platforms\\leetcode\\index.js", "source_location": "L343"}, {"caller_nid": "index_leetcodehandler_buildfileset", "callee": "push", "source_file": "V:\\Code\\ProjectCode\\CodeLedger\\src\\handlers\\platforms\\leetcode\\index.js", "source_location": "L359"}, {"caller_nid": "index_leetcodehandler_buildfileset", "callee": "join", "source_file": "V:\\Code\\ProjectCode\\CodeLedger\\src\\handlers\\platforms\\leetcode\\index.js", "source_location": "L361"}, {"caller_nid": "index_leetcodehandler_buildfileset", "callee": "map", "source_file": "V:\\Code\\ProjectCode\\CodeLedger\\src\\handlers\\platforms\\leetcode\\index.js", "source_location": "L364"}, {"caller_nid": "index_leetcodehandler_formatstats", "callee": "push", "source_file": "V:\\Code\\ProjectCode\\CodeLedger\\src\\handlers\\platforms\\leetcode\\index.js", "source_location": "L374"}, {"caller_nid": "index_leetcodehandler_formatstats", "callee": "toFixed", "source_file": "V:\\Code\\ProjectCode\\CodeLedger\\src\\handlers\\platforms\\leetcode\\index.js", "source_location": "L374"}, {"caller_nid": "index_leetcodehandler_formatstats", "callee": "push", "source_file": "V:\\Code\\ProjectCode\\CodeLedger\\src\\handlers\\platforms\\leetcode\\index.js", "source_location": "L375"}, {"caller_nid": "index_leetcodehandler_formatstats", "callee": "toFixed", "source_file": "V:\\Code\\ProjectCode\\CodeLedger\\src\\handlers\\platforms\\leetcode\\index.js", "source_location": "L375"}, {"caller_nid": "index_leetcodehandler_formatstats", "callee": "join", "source_file": "V:\\Code\\ProjectCode\\CodeLedger\\src\\handlers\\platforms\\leetcode\\index.js", "source_location": "L377"}, {"caller_nid": "index_leetcodehandler_formatstats", "callee": "map", "source_file": "V:\\Code\\ProjectCode\\CodeLedger\\src\\handlers\\platforms\\leetcode\\index.js", "source_location": "L377"}, {"caller_nid": "index_leetcodehandler_formatsimilar", "callee": "slice", "source_file": "V:\\Code\\ProjectCode\\CodeLedger\\src\\handlers\\platforms\\leetcode\\index.js", "source_location": "L382"}, {"caller_nid": "index_leetcodehandler_formatsimilar", "callee": "filter", "source_file": "V:\\Code\\ProjectCode\\CodeLedger\\src\\handlers\\platforms\\leetcode\\index.js", "source_location": "L382"}, {"caller_nid": "index_leetcodehandler_formatsimilar", "callee": "join", "source_file": "V:\\Code\\ProjectCode\\CodeLedger\\src\\handlers\\platforms\\leetcode\\index.js", "source_location": "L384"}, {"caller_nid": "index_leetcodehandler_formatsimilar", "callee": "map", "source_file": "V:\\Code\\ProjectCode\\CodeLedger\\src\\handlers\\platforms\\leetcode\\index.js", "source_location": "L387"}, {"caller_nid": "index_leetcodehandler_gql", "callee": "fetch", "source_file": "V:\\Code\\ProjectCode\\CodeLedger\\src\\handlers\\platforms\\leetcode\\index.js", "source_location": "L408"}, {"caller_nid": "index_leetcodehandler_gql", "callee": "stringify", "source_file": "V:\\Code\\ProjectCode\\CodeLedger\\src\\handlers\\platforms\\leetcode\\index.js", "source_location": "L415"}, {"caller_nid": "index_leetcodehandler_gql", "callee": "json", "source_file": "V:\\Code\\ProjectCode\\CodeLedger\\src\\handlers\\platforms\\leetcode\\index.js", "source_location": "L417"}]}